README.md
setup.cfg
setup.py
ak7_distributions.egg-info/PKG-INFO
ak7_distributions.egg-info/SOURCES.txt
ak7_distributions.egg-info/dependency_links.txt
ak7_distributions.egg-info/not-zip-safe
ak7_distributions.egg-info/top_level.txt
distributions/Binomialdistribution.py
distributions/Gaussiandistribution.py
distributions/Generaldistribution.py
distributions/__init__.py