Metadata-Version: 1.0
Name: ak7-distributions
Version: 0.1
Summary: A test case of Gaussian distributions
Home-page: UNKNOWN
Author: Aashis Kumar
Author-email: aashismanav@gmail.com
License: UNKNOWN
Platform: UNKNOWN
